rdk_performance_node/__init__.py
rdk_performance_node/app.py
rdk_performance_node/static/echarts.min.js
rdk_performance_node/static/niceButton.css
rdk_performance_node/static/rdks100_getState.js
rdk_performance_node/static/rdkultra_getState.js
rdk_performance_node/static/rdkx3_getState.js
rdk_performance_node/static/rdkx5_getState.js
rdk_performance_node/static/images/favicon.png
rdk_performance_node/static/images/logo-HorizonDeveloper.svg
rdk_performance_node/templates/rdks100.html
rdk_performance_node/templates/rdks100_wide.html
rdk_performance_node/templates/rdkultra.html
rdk_performance_node/templates/rdkultra_wide.html
rdk_performance_node/templates/rdkx3.html
rdk_performance_node/templates/rdkx3_wide.html
rdk_performance_node/templates/rdkx5.html
rdk_performance_node/templates/rdkx5_wide.html
rdk_performance_node-1.0.0.dist-info/licenses/LICENSE
rdk_performance_node-1.0.0.dist-info/METADATA
rdk_performance_node-1.0.0.dist-info/WHEEL
rdk_performance_node-1.0.0.dist-info/entry_points.txt
rdk_performance_node-1.0.0.dist-info/top_level.txt
rdk_performance_node-1.0.0.dist-info/RECORD
