Metadata-Version: 2.4
Name: rdk_performance_node
Version: 1.0.0
Summary: Web-based hardware monitoring node for RDK devices
Home-page: https://developer.d-robotics.cc/nodehubdetail/1887025046701215746
Author: D-Robotics
Author-email: D-Robotics <developer@d-robotics.cc>
License: Apache-2.0
Classifier: Development Status :: 4 - Beta
Classifier: Intended Audience :: Developers
Classifier: License :: OSI Approved :: Apache Software License
Classifier: Programming Language :: Python :: 3
Classifier: Programming Language :: Python :: 3.8
Classifier: Programming Language :: Python :: 3.9
Classifier: Programming Language :: Python :: 3.10
Requires-Python: >=3.8
License-File: LICENSE
Requires-Dist: flask==2.3.3
Requires-Dist: psutil==5.9.8
Dynamic: license-file
